{
  "main": {
    "id": "292d61c660f77116",
    "type": "split",
    "children": [
      {
        "id": "9c89de906cc5aa2a",
        "type": "tabs",
        "children": [
          {
            "id": "bac79a758c709655",
            "type": "leaf",
            "state": {
              "type": "markdown",
              "state": {
                "file": "0. 제안서/★경기도 교육청 AI/교육공동체 아키텍처 구성도.md",
                "mode": "source",
                "source": false
              },
              "icon": "lucide-file",
              "title": "교육공동체 아키텍처 구성도"
            }
          },
          {
            "id": "9f4eea16c8432d8a",
            "type": "leaf",
            "state": {
              "type": "markdown",
              "state": {
                "file": "conflict-files-obsidian-git.md",
                "mode": "source",
                "source": false
              },
              "icon": "lucide-file",
              "title": "conflict-files-obsidian-git"
            }
          }
        ],
        "currentTab": 1
      }
    ],
    "direction": "vertical"
  },
  "left": {
    "id": "4dd10addd17a5e9b",
    "type": "split",
    "children": [
      {
        "id": "6b437889ed0fdd3d",
        "type": "tabs",
        "children": [
          {
            "id": "37d1a63f9f3fc179",
            "type": "leaf",
            "state": {
              "type": "file-explorer",
              "state": {
                "sortOrder": "alphabetical",
                "autoReveal": false
              },
              "icon": "lucide-folder-closed",
              "title": "파일 탐색기"
            }
          },
          {
            "id": "27b4c92124bda587",
            "type": "leaf",
            "state": {
              "type": "search",
              "state": {
                "query": "",
                "matchingCase": false,
                "explainSearch": false,
                "collapseAll": false,
                "extraContext": false,
                "sortOrder": "alphabetical"
              },
              "icon": "lucide-search",
              "title": "검색"
            }
          },
          {
            "id": "6e3cf41817e092f5",
            "type": "leaf",
            "state": {
              "type": "bookmarks",
              "state": {},
              "icon": "lucide-bookmark",
              "title": "Bookmarks"
            }
          }
        ]
      }
    ],
    "direction": "horizontal",
    "width": 300
  },
  "right": {
    "id": "11d96b444f32b8a2",
    "type": "split",
    "children": [
      {
        "id": "5378967865c7ab83",
        "type": "tabs",
        "children": [
          {
            "id": "9b1c83d79ecaace2",
            "type": "leaf",
            "state": {
              "type": "backlink",
              "state": {
                "file": "0. 제안서 작성 참고자료/주차장 정보 데이터.md",
                "collapseAll": false,
                "extraContext": false,
                "sortOrder": "alphabetical",
                "showSearch": false,
                "searchQuery": "",
                "backlinkCollapsed": false,
                "unlinkedCollapsed": true
              },
              "icon": "links-coming-in",
              "title": "주차장 정보 데이터의 백링크"
            }
          },
          {
            "id": "c8d2d41ba3eea500",
            "type": "leaf",
            "state": {
              "type": "outgoing-link",
              "state": {
                "file": "0. 제안서 작성 참고자료/주차장 정보 데이터.md",
                "linksCollapsed": false,
                "unlinkedCollapsed": true
              },
              "icon": "links-going-out",
              "title": "주차장 정보 데이터의 나가는 링크"
            }
          },
          {
            "id": "2e8e6c9408770de2",
            "type": "leaf",
            "state": {
              "type": "tag",
              "state": {
                "sortOrder": "frequency",
                "useHierarchy": true
              },
              "icon": "lucide-tags",
              "title": "Tags"
            }
          },
          {
            "id": "fcfecf9124cd7042",
            "type": "leaf",
            "state": {
              "type": "outline",
              "state": {
                "file": "0. 제안서 작성 참고자료/주차장 정보 데이터.md"
              },
              "icon": "lucide-list",
              "title": "주차장 정보 데이터 개요"
            }
          },
          {
            "id": "9d569c5ad6a5775d",
            "type": "leaf",
            "state": {
              "type": "git-view",
              "state": {},
              "icon": "git-pull-request",
              "title": "Source Control"
            }
          }
        ],
        "currentTab": 4
      }
    ],
    "direction": "horizontal",
    "width": 300
  },
  "left-ribbon": {
    "hiddenItems": {
      "switcher:빠른 전환기 열기": false,
      "daily-notes:오늘의 일일 노트 열기": false,
      "graph:그래프 뷰 열기": false,
      "canvas:새 캔버스 만들기": false,
      "templates:템플릿 삽입": false,
      "command-palette:명령어 팔레트 열기": false,
      "obsidian-git:Open Git source control": false,
      "obsidian-omnivore:Omnivore": false
    }
  },
  "floating": {
    "id": "684a57669e93f618",
    "type": "floating",
    "children": [
      {
        "id": "35957d900b9098a6",
        "type": "window",
        "children": [
          {
            "id": "fee5bb703aa3d112",
            "type": "tabs",
            "children": [
              {
                "id": "331108796971dc75",
                "type": "leaf",
                "state": {
                  "type": "markdown",
                  "state": {
                    "file": "0. 제안서/★경기도 교육청 AI/다) 생성형 AI를 활용한 대화형 서비스 기능 (관리자).md",
                    "mode": "source",
                    "source": false
                  },
                  "icon": "lucide-file",
                  "title": "다) 생성형 AI를 활용한 대화형 서비스 기능 (관리자)"
                }
              }
            ]
          }
        ],
        "direction": "vertical",
        "x": 1621,
        "y": 35,
        "width": 605,
        "height": 605,
        "maximize": false,
        "zoom": 0
      }
    ]
  },
  "active": "9f4eea16c8432d8a",
  "lastOpenFiles": [
    "0. 제안서/★경기도 교육청 AI/교육공동체 아키텍처 구성도.md",
    "conflict-files-obsidian-git.md",
    "attatchment/ebook_638_202104230508433430.pdf",
    "attatchment/ebook_638_202104230508433430 (1).pdf",
    "attatchment/The Roles of the National Health Insurance Service in the Public Health Security.pdf",
    "attatchment/BZ202304198568815.pdf",
    "attatchment/BZ202304198568815 1.pdf",
    "attatchment/20200708.pdf",
    "attatchment/20190415(배포즉시)_심사평가원, 건강보험 운영 노하우 바탕으로 350여억원 경제적 가치 창출 (1).hwp",
    "2. 바레인 심평원/재정 건전성 향상 효과.md",
    "2. 바레인 심평원/진료비 과다청구 칼 빼든다..md",
    "2. 바레인 심평원/심평원 시스템의 국제적 인정 사례와 그 의미를 분석.md",
    "2. 바레인 심평원/우리나라 건강보험 시스템이 국제기구에서 받은 평가 내용.md",
    "2. 바레인 심평원/심사평가원의 글로벌 수출 사례와 그 영향력.md",
    "2. 바레인 심평원/부정수급 방지를 위한 정책과 기술의 차이점.md",
    "2. 바레인 심평원/복지부, 국제혁신박람회에 세계 최고수준의 보건의료정보시스템 선보여.md",
    "2. 바레인 심평원/국내 보건의료정보시스템의 기술적 강점과 경쟁력.md",
    "2. 바레인 심평원/급여 분석해 과잉진료 예방.md",
    "2. 바레인 심평원/WHO와 세계은행이 제시하는 글로벌 건강보장 지표와 한국의 성과 차이를 분석.md",
    "2. 바레인 심평원/NHIS 시스템 개선으로 기대되는 재정 건전성 향상 효과.md",
    "2. 바레인 심평원/NHIS 부정수급 감시체계의 기술적 도입 사례.md",
    "2. 바레인 심평원/HIRA 시스템’이 감염병 확산 방지에 미친 효과와 영향력.md",
    "2. 바레인 심평원/HIRA 시스템이 감염병 확산 방지에 어떤 역할을 했나.md",
    "2. 바레인 심평원/Health Insurance Review and Assessment Service.md",
    "2. 바레인 심평원/3. NHIS 시스템으로 의료비 과다 청구나 부정수급 방지 및 예방.md",
    "2. 바레인 심평원/2. 심사평가원 HIRA 시스템이 백신관리에 미친 효과와 영향력.md",
    "2. 바레인 심평원/(특별기고) 건강보험 40년, 본격 해외 진출.md",
    "2. 바레인 심평원/1. 건강보험 심사평가.md",
    "2. 바레인 심평원",
    "0. 제안서/★경기도 교육청 AI/다) 생성형 AI를 활용한 대화형 서비스 기능 (관리자).md",
    "0. 제안서/★경기도 교육청 AI/가) 생성형 AI를 활용한 서비스 공통.md",
    "0. 제안서/★경기도 교육청 AI/가) 교육행정업무 생성형 AI 대화형 서비스 기능 (사용자).md",
    "과금.md",
    "attatchment/Pasted image 20250609103606.png",
    "attatchment/Pasted image 20250609102959.png",
    "attatchment/Pasted image 20250609102933.png",
    "attatchment/Pasted image 20250522171105.png",
    "attatchment/Pasted image 20250522155427.png",
    "attatchment/Pasted image 20250522155354.png",
    "attatchment/Pasted image 20250522155156.png",
    "attatchment/Pasted image 20250522114932.png",
    "attatchment/Pasted image 20250522101801.png",
    "attatchment/Pasted image 20250521151627.png",
    "attatchment/health_check_detail.mermaid",
    "attatchment"
  ]
}